LICENSE
djognito/__init__.py
djognito/authentication.py
djognito/jwt_utils.py
djognito-0.1.1.dist-info/LICENSE
djognito-0.1.1.dist-info/WHEEL
djognito-0.1.1.dist-info/METADATA
djognito-0.1.1.dist-info/RECORD
